wrapipy/__init__.py
wrapipy/swagger.py
wrapipy/wrapi.py
wrapipy-2.0.1.dist-info/LICENSE
wrapipy-2.0.1.dist-info/METADATA
wrapipy-2.0.1.dist-info/WHEEL
wrapipy-2.0.1.dist-info/RECORD
