Metadata-Version: 2.3
Name: wrapipy
Version: 2.0.1
Summary: Simple API wrapper.
License: GNU GPLv3
Author: Chris 'Scar(R)ed' Vajdik
Author-email: chrisquackless@duck.com
Requires-Python: >=3.10
Classifier: Programming Language :: Python :: 3
Classifier: Operating System :: OS Independent
Requires-Dist: beautifulsoup4 (>=4.13.3,<5.0.0)
Requires-Dist: numpy (>=2.2.3,<3.0.0)
Requires-Dist: pydantic (>=2.11.2,<3.0.0)
Requires-Dist: requests (>=2.32.3,<3.0.0)
Project-URL: Documentation, https://wrapi-documentation.onrender.com
Project-URL: Repository, https://gitlab.com/scarred-libraries/wrapi
